blankspacebaby/__init__.py
blankspacebaby/char.py
blankspacebaby/cli.py
blankspacebaby/main.py
blankspacebaby-0.0.4.dist-info/LICENSE
blankspacebaby-0.0.4.dist-info/METADATA
blankspacebaby-0.0.4.dist-info/WHEEL
blankspacebaby-0.0.4.dist-info/entry_points.txt
blankspacebaby-0.0.4.dist-info/top_level.txt
blankspacebaby-0.0.4.dist-info/RECORD
