Metadata-Version: 2.1
Name: blankspacebaby
Version: 0.0.4
Summary: How to Typeset Chinese and English Text
Home-page: https://github.com/hongsheng-lai/BlankSpaceBaby/
Author: Hong-Sheng Lai
Author-email: jl900613@gmail.com
Classifier: Programming Language :: Python :: 3
Classifier: License :: OSI Approved :: MIT License
Classifier: Operating System :: OS Independent
Requires-Python: >=3.6
License-File: LICENSE
Requires-Dist: click (>=8.0.0)
